{"mainImage":{"path":"16821"},"allImages":[{"path":"16821"},{"path":"35577"}],"name":"Refrigerator Vestfrost 379RRETRO - 190x60x63, 315 Litres, A+ , RED RETRO","origPrice":2.669,"origAbout":"For those who value both excellent design and functionality, and who enjoy experimenting with different styles, Vestfrost has redefined the modern fridge-freezer. The retro line is characterized by stylish design, rounded corners and a sleek finish of the interior \u2013 all of this combined with advanced technological solutions. Thanks to NoFrost Multi, frost and ice do not build up on the walls of the fridge and freezer. Food is cooled evenly, does not dry out and stays fresh longer. Odors do not spread between the fridge and freezer compartments.","details":[{"name":"Brand","value":"Vestfrost"},{"name":"Annual Energy Consumption (kW/Year), kilowatt per hour per Year","value":"292"},{"name":"Energy Efficiency Class","value":"A+"},{"name":"Depth (mm), millimeter","value":"631"},{"name":"Height (mm), millimeter","value":"1901"},{"name":"Width (mm), millimeter","value":"605"},{"name":"Refrigerator Cooling System თანამბრად ანაწილებს ჰაერის ნაკადს მაცივარ კამერაში.","value":"Static"},{"name":"Refrigerating Chamber Capacity (L), liter","value":"205"},{"name":"Ice Tray (Yes/No)","value":"Yes"},{"name":"Freezing Power Capacity (kg/day), kilogram per day","value":"4.5"},{"name":"Freezer Location","value":"Bottom"},{"name":"Freezer Cooling System","value":"Static"},{"name":"Freezer Capacity (L), liter","value":"86"},{"name":"Control","value":"Mechanical"},{"name":"Compressor Type","value":"Standard"},{"name":"Color","value":"Blue"},{"name":"Climate Class","value":"SN-T"},{"name":"Installation Type","value":"Free-Standing"},{"name":"Type","value":"Regular"},{"name":"Warranty (months)","value":"36"}],"PId":78249,"category":"Refrigerators"}