{"mainImage":{"path":"16569"},"allImages":[],"name":"Athlon 3000G 8GB 240GB SSD Radeon Graphics","origPrice":749,"origAbout":"","details":[{"name":"Brand","value":"Metromart"},{"name":"CPU","value":"AMD Athlon"},{"name":"CPU Model","value":"3000G"},{"name":"CPU Cache","value":"4 MB"},{"name":"CPU Lithography","value":"14nm"},{"name":"CPU Boost Speed (GHz)","value":"3.5"},{"name":"Number of CPU Cores/Threads","value":"2 Cores 4 Threads"},{"name":"CPU Series","value":"Picasso"},{"name":"Memory (RAM)","value":"8 GB"},{"name":"Memory (RAM) Type","value":"DDR4"},{"name":"Memory Frequency","value":"2666 MHz"},{"name":"HDD/SSD/Flash","value":"SSD"},{"name":"HDD/SSD/Flash Capacity","value":"240 GB"},{"name":"Graphics Adapter Type","value":"Integrated"},{"name":"Operating System","value":"FreeDOS"},{"name":"Motherboard","value":"Asus A320MH"},{"name":"Power Supply (W)","value":"450"},{"name":"Cooler","value":"Yes"},{"name":"PC Case","value":"Golden Field NX2"},{"name":"Color","value":"Black"},{"name":"Warranty (months)","value":"24"}],"PId":25595,"category":"Desktop"}