{"mainImage":{"path":"16557"},"allImages":[{"path":"16557"},{"path":"35153"},{"path":"35154"}],"name":"TV LG 77\" (195.58cm) / OLED77C24LA Smart 4K UHD","origPrice":1.599,"origAbout":"","details":[{"name":"Brand","value":"LG"},{"name":"Display Diagonal","value":"77\" (195cm)"},{"name":"Display Resolution","value":"3840x2160 4K UHD"},{"name":"Display Type","value":"OLED"},{"name":"Screen Refresh Rate","value":"120 Hz"},{"name":"HDR Support","value":"HDR10 Pro"},{"name":"CPU Cores","value":"4 Cores"},{"name":"Bluetooth","value":"Yes"},{"name":"RJ-45 (LAN)","value":"Yes"},{"name":"Wi-Fi","value":"Yes"},{"name":"HDMI High-sharpness multimedia interface","value":"4"},{"name":"Number of Speakers","value":"2"},{"name":"Weight with Stand (kg)","value":"27.1"},{"name":"Weight w/o Stand (kg)","value":"23.5"},{"name":"Model/Part Number","value":"OLED77C24LA"},{"name":"Operating System","value":"WebOS"},{"name":"Video processor","value":"Quantum Processor 4K"},{"name":"Speaker Power","value":"40 W"},{"name":"DVB-C","value":"Yes"},{"name":"DVB-T","value":"Yes"},{"name":"DVB-T2","value":"Yes"},{"name":"DVB-S","value":"Yes"},{"name":"DVB-S2","value":"Yes"},{"name":"Number of USB Ports","value":"3"},{"name":"CI Slot","value":"Yes"},{"name":"VESA","value":"300x200"},{"name":"Dimensions with Stand","value":"1711x1035x243"},{"name":"Dimensions w/o Stand","value":"1711x982x47.1"},{"name":"4K HFR","value":"Yes"},{"name":"AI Brightness Control","value":"Yes"},{"name":"AI Upscaling","value":"Yes"},{"name":"AV1 (Video Decoder)","value":"Yes"},{"name":"Browser (Yes/No)","value":"Yes"},{"name":"Color","value":"Dark Titan Silver"},{"name":"Dimming Algorithm","value":"Local Dimming"},{"name":"DOLBY ATMOS","value":"Yes"},{"name":"Dolby Vision","value":"Yes"},{"name":"Dolby Digital","value":"Yes"},{"name":"FreeSync Compatible","value":"Yes"},{"name":"HEVC","value":"Yes"},{"name":"HGIG Mode","value":"Yes"},{"name":"HLG","value":"Yes"},{"name":"Optical Audio","value":"Yes"},{"name":"Picture Modes","value":"Yes"},{"name":"Remote Control","value":"Yes"},{"name":"RF In","value":"Yes"},{"name":"RF Satellite Input","value":"Yes"},{"name":"Supported Media","value":"Video, Audio, Picture"},{"name":"VP9 (Video Decoder)","value":"Yes"},{"name":"Type","value":"Smart TV"},{"name":"Warranty (months)","value":"24"}],"PId":94911,"category":"Smart-TV"}