{"mainImage":{"path":"16999"},"allImages":[{"path":"16999"},{"path":"35741"},{"path":"35742"}],"name":"TV TCL 50\" (128cm) / 50C635/R51MG8S-RU/GE Smart 4K UHD","origPrice":4.299,"origAbout":"","details":[{"name":"Brand","value":"TCL"},{"name":"Display Diagonal","value":"50\" (127cm)"},{"name":"Display Resolution","value":"3840x2160 4K UHD"},{"name":"Display Type","value":"QLED"},{"name":"Backlighting Type","value":"DLED"},{"name":"Screen Refresh Rate","value":"60 Hz"},{"name":"HDR Support","value":"HDR10+"},{"name":"Picture Format","value":"16:9"},{"name":"Contrast","value":"6000:1"},{"name":"Viewing Angle","value":"178° / 178°"},{"name":"Bluetooth","value":"Yes"},{"name":"RJ-45 (LAN)","value":"Yes"},{"name":"Wi-Fi","value":"Yes"},{"name":"HDMI High-sharpness multimedia interface","value":"3"},{"name":"Number of Speakers","value":"2"},{"name":"Weight with Stand (kg)","value":"10.76"},{"name":"Weight w/o Stand (kg)","value":"10.37"},{"name":"Model/Part Number","value":"50C635/R51MG8S-RU/GE"},{"name":"Operating System","value":"Google TV"},{"name":"Speaker Power","value":"20 W"},{"name":"DVB-T","value":"Yes"},{"name":"Number of USB Ports","value":"2"},{"name":"VESA","value":"300x300"},{"name":"Dimensions with Stand","value":"1112x700x290"},{"name":"Dimensions w/o Stand","value":"1112x636x79"},{"name":"Browser (Yes/No)","value":"Yes"},{"name":"Color","value":"Black"},{"name":"DOLBY ATMOS","value":"Yes"},{"name":"Dolby Vision","value":"Yes"},{"name":"Remote Control","value":"Yes"},{"name":"Supported Media","value":"Video, Audio, Picture"},{"name":"TV Processing Engine","value":"ARM Cortex-A55"},{"name":"Type","value":"Smart TV"},{"name":"Warranty (months)","value":"24"}],"PId":56946,"category":"Smart-TV"}