{"mainImage":{"path":"7276"},"allImages":[],"name":"Microwave Samsung (ME88SUW/BW)","origPrice":279,"origAbout":"The durable BIOceramic coating is easy to clean and won't scratch. Its smooth surface can be cleaned without harsh cleaning agents. In addition, the coating does not lose color after long-term use. Accelerated defrost: this function allows you to defrost food quickly and evenly. You can enjoy the great taste of your favorite food at any time of the year.","details":[{"name":"Brand","value":"Samsung"},{"name":"Microwave Output Power (W)","value":"1150"},{"name":"Weight (kg), kilogram","value":"12"},{"name":"Volume (L)","value":"23"},{"name":"Control","value":"Mechanical"},{"name":"Switch Type","value":"Button"},{"name":"Dimensions (HxWxD)","value":"27 x 48 x 35 cm"},{"name":"Number of Programs","value":"6"},{"name":"Type","value":"Free-Standing"},{"name":"Warranty (months)","value":"24"}],"PId":70776,"category":"Microwave"}